RHash-1.4.2.data/data/librhash.dll
RHash-1.4.2.data/purelib/rhash.py
RHash-1.4.2.dist-info/COPYING
RHash-1.4.2.dist-info/METADATA
RHash-1.4.2.dist-info/WHEEL
RHash-1.4.2.dist-info/top_level.txt
RHash-1.4.2.dist-info/RECORD
