Metadata-Version: 2.1
Name: RHash
Version: 1.4.2
Summary: Windows binary wheels for RHash
Home-page: https://github.com/rhash/RHash
Maintainer: Dobatymo
License: UNKNOWN
Platform: UNKNOWN
Classifier: Development Status :: 5 - Production/Stable
Classifier: Intended Audience :: Developers
Classifier: Intended Audience :: Science/Research
Classifier: Operating System :: Microsoft :: Windows
Classifier: Programming Language :: Python :: 2
Classifier: Programming Language :: Python :: 3
Classifier: Topic :: Internet
Classifier: Topic :: Scientific/Engineering
Classifier: Topic :: Utilities
License-File: COPYING
